modelgauge/tests/bbq.py
modelgauge/tests/discrim_eval.py
modelgauge/tests/real_toxicity_prompts.py
modelgauge/tests/simple_safety_tests.py
modelgauge/tests/xstest.py
modelgauge_standard_tests-0.6.3.dist-info/METADATA
modelgauge_standard_tests-0.6.3.dist-info/WHEEL
modelgauge_standard_tests-0.6.3.dist-info/RECORD
