Metadata-Version: 2.1
Name: modelgauge-standard-tests
Version: 0.6.3
Summary: 
Author: MLCommons AI Safety
Author-email: ai-safety-engineering@mlcommons.org
Requires-Python: >=3.10,<4.0
Classifier: Programming Language :: Python :: 3
Classifier: Programming Language :: Python :: 3.10
Classifier: Programming Language :: Python :: 3.11
Classifier: Programming Language :: Python :: 3.12
Requires-Dist: modelgauge_openai
Requires-Dist: modelgauge_perspective_api
Requires-Dist: pandas (>=2.2.1,<3.0.0)
Requires-Dist: pandas-stubs (>=2.2.1.240316,<3.0.0.0)
Requires-Dist: scikit-learn (>=1.4.1.post1,<2.0.0)
Requires-Dist: statsmodels (>=0.14.1,<0.15.0)
